setup.py
awsnd_sst_probdist/Binomialdistribution.py
awsnd_sst_probdist/Gaussiandistribution.py
awsnd_sst_probdist/Generaldistribution.py
awsnd_sst_probdist/__init__.py
awsnd_sst_probdist.egg-info/PKG-INFO
awsnd_sst_probdist.egg-info/SOURCES.txt
awsnd_sst_probdist.egg-info/dependency_links.txt
awsnd_sst_probdist.egg-info/not-zip-safe
awsnd_sst_probdist.egg-info/top_level.txt