Metadata-Version: 1.0
Name: awsnd-sst-probdist
Version: 0.2
Summary: Binomial and Gaussian probability distributions
Home-page: UNKNOWN
Author: UNKNOWN
Author-email: saulotoledo@gmail.com
License: UNKNOWN
Platform: UNKNOWN
